{
	"global": {
		"settings": {
			"color": {
				"gradients": [ ],
				"palette": [
					{
						"slug": "background",
						"value": "#FFFFFF"
					},
					{
						"slug": "foreground",
						"value": "#333333"
					},
					{
						"slug": "primary",
						"value": "#000000"
					},
					{
						"slug": "secondary",
						"value": "#3C8067"
					},
					{
						"slug": "tertiary",
						"value": "#FAFBF6"
					}
				]
			},
			"typography": {
				"customFontSize": true,
				"customLineHeight": true,
				"fontSizes": [
					{
						"slug": "tiny",
						"value": "14px"
					},
					{
						"slug": "small",
						"value": "16px"
					},
					{
						"slug": "medium",
						"value": "18px"
					},
					{
						"slug": "large",
						"value": "24px"
					},
					{
						"slug": "extra-large",
						"value": "28px"
					},
					{
						"slug": "huge",
						"value": "32px"
					},
					{
						"slug": "gigantic",
						"value": "48px"
					}
				],
				"spacing": {
					"customPadding": true,
					"units": [ "px", "em", "rem", "vh", "vw" ]
				}
			}
		}
	}
}