{
    "settings": {
        "options": [],
        "theme_mods": {
            "0": false,
            "nav_menu_locations": {
                "primary": "primary",
                "social": "social-links"
            },
            "header_textcolor": "1a1a1a",
            "header_image": "remove-header",
            "colors_manager": {
                "colors": {
                    "bg": "#1a1a1a",
                    "txt": "#ffffff",
                    "link": "#007acc",
                    "fg1": "#1a1a1a",
                    "fg2": "#686868"
                },
                "cached": false
            }
        },
        "headstart": {
            "mapped_id_options": [],
            "mapped_id_theme_mods": []
        }
    },
    "widgets": [
        {
            "id": "text-2",
            "id_base": "text",
            "settings": {
                "title": "Metin Pencere Öğesi",
                "text": "Bu bir metin pencere öğesidir. Bu, kenar çubuğunuza metin veya HTML eklemenizi sağlayan bir metin pencere öğesidir. Metinleri, bağlantıları, görüntüleri HTML'i veya bunların bir birleşimini görüntülemek için bir metin pencere öğesi kullanabilirsiniz. Bunları <a href=\"https://wordpress.com/customize/\">Özelleştirici</a>'nin Pencere Öğesi bölümünde düzenleyin.",
                "filter": false,
                "syntaxhighlighter_encoded": true
            },
            "sidebar": "sidebar-1",
            "position": 0
        },
        {
            "id": "search-2",
            "id_base": "search",
            "settings": {
                "title": ""
            },
            "sidebar": "sidebar-1",
            "position": 1
        },
        {
            "id": "recent-posts-2",
            "id_base": "recent-posts",
            "settings": {
                "title": "",
                "number": 5,
                "show_date": true
            },
            "sidebar": "sidebar-2",
            "position": 0
        }
    ],
    "content": [
        {
            "post_title": "Hakkında",
            "post_content": "Bu bir hakkında sayfası örneğidir. Gönderilerin aksine sayfalar, Hakkında ya da İletişim gibi kolayca ulaşılabilir, zamandan bağımsız içerikleriniz için daha uygundur. Bu sayfada değişiklik yapmak için Düzenle'ye tıklayın veya <a href=\"https://wordpress.com/page\">başka bir sayfa ekleyin</a>.",
            "post_excerpt": "Bu yalnızca hakkında&nbsp;sayfası için kısa bir alıntıdır.",
            "post_status": "publish",
            "menu_order": 1,
            "comment_status": "closed",
            "ping_status": "closed",
            "post_type": "page",
            "hs_custom_meta": "_hs_about_page",
            "hs_sharing": 1,
            "hs_old_id": 102,
            "hs_like_status": 1
        },
        {
            "post_title": "İletişim",
            "post_content": "Bu, bazı temel bilgilerin ve bir iletişim formunun yer aldığı bir iletişim sayfasıdır. [contact-form][contact-field label=\"Ad\" type=\"name\" required=\"1\"/][contact-field label=\"E-posta\" type=\"email\" required=\"1\"/][contact-field label=\"Web sitesi\" type=\"url\"/][contact-field label=\"Yorum\" type=\"textarea\" required=\"1\"/][/contact-form]",
            "post_excerpt": "Bu yalnızca iletişim&nbsp;sayfası için kısa bir alıntıdır.",
            "post_status": "publish",
            "menu_order": 2,
            "comment_status": "closed",
            "ping_status": "closed",
            "post_type": "page",
            "hs_custom_meta": "_hs_contact_page",
            "hs_sharing": 1,
            "hs_old_id": 103,
            "hs_like_status": 1
        },
        {
            "post_title": "İlk blog gönderisi",
            "post_content": "Bu ilk gönderiniz. Değiştirmek veya silmek için Düzenle'ye tıklayın veya <a href=\"https://wordpress.com/post\">yeni bir gönderi başlatın</a>. İsterseniz okuyuculara bu blogu yazmaya neden başladığınızı ve ne yapmayı planladığınızı söylemek için bu gönderiyi kullanın.\n\n<img class=\"wp-image-7 size-full\" src=\"https://twentysixteendemo.files.wordpress.com/2015/11/post.png\" alt=\"yazı\" width=\"1000\" height=\"563\"  />",
            "post_excerpt": "Bu, gönderi alıntısıdır.",
            "post_status": "publish",
            "comment_status": "open",
            "ping_status": "open",
            "post_type": "post",
            "hs_custom_meta": "_hs_first_post",
            "hs_sharing": 1,
            "hs_like_status": 0,
            "hs_old_id": 104,
            "sticky": true
        }
    ],
    "menus": {
        "social-links": {
            "name": "Sosyal Bağlantılar",
            "items": [
                {
                    "menu-item-title": "Twitter",
                    "menu-item-db-id": 104,
                    "menu-item-object-id": "104",
                    "menu-item-object": "custom",
                    "menu-item-type": "custom",
                    "menu-item-status": "publish",
                    "menu-item-position": 1,
                    "menu-item-parent-id": "0",
                    "menu-item-description": "",
                    "menu-item-url": "https://twitter.com/"
                },
                {
                    "menu-item-title": "Facebook",
                    "menu-item-db-id": 105,
                    "menu-item-object-id": "105",
                    "menu-item-object": "custom",
                    "menu-item-type": "custom",
                    "menu-item-status": "publish",
                    "menu-item-position": 2,
                    "menu-item-parent-id": "0",
                    "menu-item-description": "",
                    "menu-item-url": "https://www.facebook.com/"
                },
                {
                    "menu-item-title": "Google+",
                    "menu-item-db-id": 106,
                    "menu-item-object-id": "106",
                    "menu-item-object": "custom",
                    "menu-item-type": "custom",
                    "menu-item-status": "publish",
                    "menu-item-position": 3,
                    "menu-item-parent-id": "0",
                    "menu-item-description": "",
                    "menu-item-url": "http://plus.google.com"
                },
                {
                    "menu-item-title": "GitHub",
                    "menu-item-db-id": 107,
                    "menu-item-object-id": "107",
                    "menu-item-object": "custom",
                    "menu-item-type": "custom",
                    "menu-item-status": "publish",
                    "menu-item-position": 4,
                    "menu-item-parent-id": "0",
                    "menu-item-description": "",
                    "menu-item-url": "http://github.com"
                },
                {
                    "menu-item-title": "WordPress.com",
                    "menu-item-db-id": 108,
                    "menu-item-object-id": "108",
                    "menu-item-object": "custom",
                    "menu-item-type": "custom",
                    "menu-item-status": "publish",
                    "menu-item-position": 5,
                    "menu-item-parent-id": "0",
                    "menu-item-description": "",
                    "menu-item-url": "http://wordpress.com"
                }
            ]
        }
    }
}