{
	"settings": {
		"color": {
			"palette": [
				{
					"color": "#285b71",
					"name": "Primary",
					"slug": "primary"
				},
				{
					"color": "#285b71",
					"name": "Secondary",
					"slug": "secondary"
				},
				{
					"color": "#25556a",
					"name": "Foreground",
					"slug": "foreground"
				},
				{
					"color": "#dce1cc",
					"name": "Background",
					"slug": "background"
				},
				{
					"color": "#285b7140",
					"name": "Tertiary",
					"slug": "tertiary"
				}
			]
		}
	},
	"styles": {
		"blocks": {
			"core/cover": {
				"filter": {
					"duotone": "var(--wp--preset--duotone--nauticalfrost)"
				}
			},
			"core/image": {
				"filter": {
					"duotone": "var(--wp--preset--duotone--nauticalfrost)"
				}
			},
			"core/site-logo": {
				"filter": {
					"duotone": "var(--wp--preset--duotone--nauticalfrost)"
				}
			}
		},
		"elements": {
			"h1": {
				"typography": {
					"fontFamily": "var(--wp--preset--font-family--anton)"
				}
			},
			"h2": {
				"typography": {
					"fontFamily": "var(--wp--preset--font-family--anton)"
				}
			},
			"h3": {
				"typography": {
					"fontFamily": "var(--wp--preset--font-family--anton)"
				}
			},
			"h4": {
				"typography": {
					"fontFamily": "var(--wp--preset--font-family--anton)"
				}
			},
			"h5": {
				"typography": {
					"fontFamily": "var(--wp--preset--font-family--anton)"
				}
			},
			"h6": {
				"typography": {
					"fontFamily": "var(--wp--preset--font-family--anton)"
				}
			},
			"heading": {
				"typography": {
					"fontFamily": "var(--wp--preset--font-family--anton)"
				}
			}
		},
		"typography": {
			"fontFamily": "var(--wp--preset--font-family--rubik)",
			"fontStyle": "normal",
			"fontWeight": "400"
		}
	},
	"title": "Nautical Frost",
	"version": 2,
	"$schema": "https://schemas.wp.org/trunk/theme.json"
}